{
  "2014-03-01": [
    {
      "CashfromOperatingActivity ": 53270.0
    },
    {
      "CashfromInvestingActivity ": -63633.0
    },
    {
      "CashfromFinancingActivity ": 15225.0
    },
    {
      "NetCashFlow": 4862.0
    }
  ],
  "2015-03-01": [
    {
      "CashfromOperatingActivity ": 33950.0
    },
    {
      "CashfromInvestingActivity ": -30058.0
    },
    {
      "CashfromFinancingActivity ": -10641.0
    },
    {
      "NetCashFlow": -6749.0
    }
  ],
  "2016-03-01": [
    {
      "CashfromOperatingActivity ": 46292.0
    },
    {
      "CashfromInvestingActivity ": -38256.0
    },
    {
      "CashfromFinancingActivity ": -8972.0
    },
    {
      "NetCashFlow": -935.0
    }
  ],
  "2017-03-01": [
    {
      "CashfromOperatingActivity ": 45780.0
    },
    {
      "CashfromInvestingActivity ": -43815.0
    },
    {
      "CashfromFinancingActivity ": -1867.0
    },
    {
      "NetCashFlow": 99.0
    }
  ],
  "2018-03-01": [
    {
      "CashfromOperatingActivity ": 56792.0
    },
    {
      "CashfromInvestingActivity ": -66798.0
    },
    {
      "CashfromFinancingActivity ": 9909.0
    },
    {
      "NetCashFlow": -97.0
    }
  ],
  "2019-03-01": [
    {
      "CashfromOperatingActivity ": 61458.0
    },
    {
      "CashfromInvestingActivity ": -37132.0
    },
    {
      "CashfromFinancingActivity ": -23324.0
    },
    {
      "NetCashFlow": 1001.0
    }
  ],
  "2020-03-01": [
    {
      "CashfromOperatingActivity ": 70593.0
    },
    {
      "CashfromInvestingActivity ": -53159.0
    },
    {
      "CashfromFinancingActivity ": -16726.0
    },
    {
      "NetCashFlow": 708.0
    }
  ],
  "2021-03-01": [
    {
      "CashfromOperatingActivity ": 47185.0
    },
    {
      "CashfromInvestingActivity ": -39141.0
    },
    {
      "CashfromFinancingActivity ": -8239.0
    },
    {
      "NetCashFlow": -195.0
    }
  ],
  "2022-03-01": [
    {
      "CashfromOperatingActivity ": 78248.0
    },
    {
      "CashfromInvestingActivity ": -41197.0
    },
    {
      "CashfromFinancingActivity ": -35790.0
    },
    {
      "NetCashFlow": 1261.0
    }
  ],
  "2023-03-01": [
    {
      "CashfromOperatingActivity ": 84211.0
    },
    {
      "CashfromInvestingActivity ": -72799.0
    },
    {
      "CashfromFinancingActivity ": -12916.0
    },
    {
      "NetCashFlow": -1504.0
    }
  ],
  "2024-03-01": [
    {
      "CashfromOperatingActivity ": 98847.0
    },
    {
      "CashfromInvestingActivity ": -57423.0
    },
    {
      "CashfromFinancingActivity ": -45009.0
    },
    {
      "NetCashFlow": -3586.0
    }
  ],
  "2025-03-01": [
    {
      "CashfromOperatingActivity ": 90868.0
    },
    {
      "CashfromInvestingActivity ": -42901.0
    },
    {
      "CashfromFinancingActivity ": -47908.0
    },
    {
      "NetCashFlow": 59.0
    }
  ]
}
