{
  "2017-03-01": [
    {
      "Promoters ": 0.5305
    },
    {
      "FIIs ": 0.2113
    },
    {
      "DIIs ": 0.050300000000000004
    },
    {
      "Government ": 0.0034999999999999996
    },
    {
      "Public ": 0.20440000000000003
    },
    {
      "Others ": 0.0
    },
    {
      "No.ofShareholders": 109516.0
    }
  ],
  "2018-03-01": [
    {
      "Promoters ": 0.5291
    },
    {
      "FIIs ": 0.2072
    },
    {
      "DIIs ": 0.0611
    },
    {
      "Government ": 0.0017000000000000001
    },
    {
      "Public ": 0.201
    },
    {
      "Others ": 0.0
    },
    {
      "No.ofShareholders": 131620.0
    }
  ],
  "2019-03-01": [
    {
      "Promoters ": 0.5291
    },
    {
      "FIIs ": 0.1924
    },
    {
      "DIIs ": 0.0721
    },
    {
      "Government ": 0.0017000000000000001
    },
    {
      "Public ": 0.2047
    },
    {
      "Others ": 0.0
    },
    {
      "No.ofShareholders": 180710.0
    }
  ],
  "2020-03-01": [
    {
      "Promoters ": 0.5291
    },
    {
      "FIIs ": 0.17739999999999997
    },
    {
      "DIIs ": 0.10869999999999999
    },
    {
      "Government ": 0.0023
    },
    {
      "Public ": 0.1826
    },
    {
      "Others ": 0.0
    },
    {
      "No.ofShareholders": 322928.0
    }
  ],
  "2021-03-01": [
    {
      "Promoters ": 0.529
    },
    {
      "FIIs ": 0.18100000000000002
    },
    {
      "DIIs ": 0.11130000000000001
    },
    {
      "Government ": 0.0034999999999999996
    },
    {
      "Public ": 0.1753
    },
    {
      "Others ": 0.0
    },
    {
      "No.ofShareholders": 355774.0
    }
  ],
  "2022-03-01": [
    {
      "Promoters ": 0.529
    },
    {
      "FIIs ": 0.184
    },
    {
      "DIIs ": 0.10210000000000001
    },
    {
      "Government ": 0.0016
    },
    {
      "Public ": 0.1833
    },
    {
      "Others ": 0.0
    },
    {
      "No.ofShareholders": 578252.0
    }
  ],
  "2023-03-01": [
    {
      "Promoters ": 0.529
    },
    {
      "FIIs ": 0.1751
    },
    {
      "DIIs ": 0.11230000000000001
    },
    {
      "Government ": 0.0017000000000000001
    },
    {
      "Public ": 0.1819
    },
    {
      "Others ": 0.0
    },
    {
      "No.ofShareholders": 719167.0
    }
  ],
  "2024-03-01": [
    {
      "Promoters ": 0.529
    },
    {
      "FIIs ": 0.19010000000000002
    },
    {
      "DIIs ": 0.10289999999999999
    },
    {
      "Government ": 0.0017000000000000001
    },
    {
      "Public ": 0.1757
    },
    {
      "Others ": 0.0008
    },
    {
      "No.ofShareholders": 749319.0
    }
  ],
  "2025-03-01": [
    {
      "Promoters ": 0.529
    },
    {
      "FIIs ": 0.1782
    },
    {
      "DIIs ": 0.1201
    },
    {
      "Government ": 0.0019
    },
    {
      "Public ": 0.17010000000000003
    },
    {
      "Others ": 0.0008
    },
    {
      "No.ofShareholders": 855126.0
    }
  ],
  "2025-12-01": [
    {
      "Promoters ": 0.529
    },
    {
      "FIIs ": 0.1555
    },
    {
      "DIIs ": 0.1483
    },
    {
      "Government ": 0.0019
    },
    {
      "Public ": 0.16449999999999998
    },
    {
      "Others ": 0.0008
    },
    {
      "No.ofShareholders": 749373.0
    }
  ]
}
