{
  "2022-12-01": [
    {
      "Revenue ": 9457.0
    },
    {
      "Interest": 4962.0
    },
    {
      "Expenses ": 3950.0
    },
    {
      "FinancingProfit": 545.0
    },
    {
      "FinancingMargin%": 0.06
    },
    {
      "OtherIncome ": 2076.0
    },
    {
      "Depreciation": 0.0
    },
    {
      "Profitbeforetax": 2622.0
    },
    {
      "Tax%": 0.25
    },
    {
      "NetProfit ": 1964.0
    },
    {
      "EPSinRs": 25.32
    },
    {
      "GrossNPA%": 0.0206
    },
    {
      "NetNPA%": 0.0062
    },
    {
      "RawPDF": "/company/source/quarter/1480/12/2022/"
    }
  ],
  "2023-03-01": [
    {
      "Revenue ": 10021.0
    },
    {
      "Interest": 5351.0
    },
    {
      "Expenses ": 4096.0
    },
    {
      "FinancingProfit": 574.0
    },
    {
      "FinancingMargin%": 0.06
    },
    {
      "OtherIncome ": 2154.0
    },
    {
      "Depreciation": 0.0
    },
    {
      "Profitbeforetax": 2727.0
    },
    {
      "Tax%": 0.25
    },
    {
      "NetProfit ": 2043.0
    },
    {
      "EPSinRs": 26.34
    },
    {
      "GrossNPA%": 0.019799999999999998
    },
    {
      "NetNPA%": 0.0059
    },
    {
      "RawPDF": "/company/source/quarter/1480/3/2023/"
    }
  ],
  "2023-06-01": [
    {
      "Revenue ": 10730.0
    },
    {
      "Interest": 5863.0
    },
    {
      "Expenses ": 4237.0
    },
    {
      "FinancingProfit": 630.0
    },
    {
      "FinancingMargin%": 0.06
    },
    {
      "OtherIncome ": 2210.0
    },
    {
      "Depreciation": 0.0
    },
    {
      "Profitbeforetax": 2840.0
    },
    {
      "Tax%": 0.25
    },
    {
      "NetProfit ": 2124.0
    },
    {
      "EPSinRs": 27.38
    },
    {
      "GrossNPA%": 0.0194
    },
    {
      "NetNPA%": 0.0058
    },
    {
      "RawPDF": "/company/source/quarter/1480/6/2023/"
    }
  ],
  "2023-09-01": [
    {
      "Revenue ": 11248.0
    },
    {
      "Interest": 6171.0
    },
    {
      "Expenses ": 4424.0
    },
    {
      "FinancingProfit": 653.0
    },
    {
      "FinancingMargin%": 0.06
    },
    {
      "OtherIncome ": 2282.0
    },
    {
      "Depreciation": 0.0
    },
    {
      "Profitbeforetax": 2935.0
    },
    {
      "Tax%": 0.25
    },
    {
      "NetProfit ": 2202.0
    },
    {
      "EPSinRs": 28.34
    },
    {
      "GrossNPA%": 0.019299999999999998
    },
    {
      "NetNPA%": 0.005699999999999999
    },
    {
      "RawPDF": "/company/source/quarter/1480/9/2023/"
    }
  ],
  "2023-12-01": [
    {
      "Revenue ": 11572.0
    },
    {
      "Interest": 6277.0
    },
    {
      "Expenses ": 4618.0
    },
    {
      "FinancingProfit": 677.0
    },
    {
      "FinancingMargin%": 0.06
    },
    {
      "OtherIncome ": 2396.0
    },
    {
      "Depreciation": 0.0
    },
    {
      "Profitbeforetax": 3073.0
    },
    {
      "Tax%": 0.25
    },
    {
      "NetProfit ": 2301.0
    },
    {
      "EPSinRs": 29.59
    },
    {
      "GrossNPA%": 0.0192
    },
    {
      "NetNPA%": 0.005699999999999999
    },
    {
      "RawPDF": "/company/source/quarter/1480/12/2023/"
    }
  ],
  "2024-03-01": [
    {
      "Revenue ": 12199.0
    },
    {
      "Interest": 6822.0
    },
    {
      "Expenses ": 4753.0
    },
    {
      "FinancingProfit": 623.0
    },
    {
      "FinancingMargin%": 0.05
    },
    {
      "OtherIncome ": 2508.0
    },
    {
      "Depreciation": 0.0
    },
    {
      "Profitbeforetax": 3131.0
    },
    {
      "Tax%": 0.25
    },
    {
      "NetProfit ": 2349.0
    },
    {
      "EPSinRs": 30.18
    },
    {
      "GrossNPA%": 0.0192
    },
    {
      "NetNPA%": 0.005699999999999999
    },
    {
      "RawPDF": "/company/source/quarter/1480/3/2024/"
    }
  ],
  "2024-06-01": [
    {
      "Revenue ": 12547.0
    },
    {
      "Interest": 7139.0
    },
    {
      "Expenses ": 4947.0
    },
    {
      "FinancingProfit": 460.0
    },
    {
      "FinancingMargin%": 0.04
    },
    {
      "OtherIncome ": 2442.0
    },
    {
      "Depreciation": 0.0
    },
    {
      "Profitbeforetax": 2902.0
    },
    {
      "Tax%": 0.25
    },
    {
      "NetProfit ": 2171.0
    },
    {
      "EPSinRs": 27.88
    },
    {
      "GrossNPA%": 0.0202
    },
    {
      "NetNPA%": 0.006
    },
    {
      "RawPDF": "/company/source/quarter/1480/6/2024/"
    }
  ],
  "2024-09-01": [
    {
      "Revenue ": 12686.0
    },
    {
      "Interest": 7339.0
    },
    {
      "Expenses ": 5752.0
    },
    {
      "FinancingProfit": -405.0
    },
    {
      "FinancingMargin%": -0.03
    },
    {
      "OtherIncome ": 2185.0
    },
    {
      "Depreciation": 0.0
    },
    {
      "Profitbeforetax": 1780.0
    },
    {
      "Tax%": 0.25
    },
    {
      "NetProfit ": 1331.0
    },
    {
      "EPSinRs": 17.09
    },
    {
      "GrossNPA%": 0.021099999999999997
    },
    {
      "NetNPA%": 0.0064
    },
    {
      "RawPDF": "/company/source/quarter/1480/9/2024/"
    }
  ],
  "2024-12-01": [
    {
      "Revenue ": 12801.0
    },
    {
      "Interest": 7573.0
    },
    {
      "Expenses ": 5726.0
    },
    {
      "FinancingProfit": -498.0
    },
    {
      "FinancingMargin%": -0.04
    },
    {
      "OtherIncome ": 2355.0
    },
    {
      "Depreciation": 0.0
    },
    {
      "Profitbeforetax": 1857.0
    },
    {
      "Tax%": 0.24
    },
    {
      "NetProfit ": 1402.0
    },
    {
      "EPSinRs": 18.0
    },
    {
      "GrossNPA%": 0.0225
    },
    {
      "NetNPA%": 0.0068000000000000005
    },
    {
      "RawPDF": "/company/source/quarter/1480/12/2024/"
    }
  ],
  "2025-03-01": [
    {
      "Revenue ": 10634.0
    },
    {
      "Interest": 7586.0
    },
    {
      "Expenses ": 6770.0
    },
    {
      "FinancingProfit": -3722.0
    },
    {
      "FinancingMargin%": -0.35
    },
    {
      "OtherIncome ": 709.0
    },
    {
      "Depreciation": 0.0
    },
    {
      "Profitbeforetax": -3013.0
    },
    {
      "Tax%": -0.23
    },
    {
      "NetProfit ": -2329.0
    },
    {
      "EPSinRs": -29.89
    },
    {
      "GrossNPA%": 0.0313
    },
    {
      "NetNPA%": 0.0095
    },
    {
      "RawPDF": "/company/source/quarter/1480/3/2025/"
    }
  ],
  "2025-06-01": [
    {
      "Revenue ": 12264.0
    },
    {
      "Interest": 7624.0
    },
    {
      "Expenses ": 5989.0
    },
    {
      "FinancingProfit": -1350.0
    },
    {
      "FinancingMargin%": -0.11
    },
    {
      "OtherIncome ": 2157.0
    },
    {
      "Depreciation": 0.0
    },
    {
      "Profitbeforetax": 807.0
    },
    {
      "Tax%": 0.25
    },
    {
      "NetProfit ": 604.0
    },
    {
      "EPSinRs": 7.75
    },
    {
      "GrossNPA%": 0.0364
    },
    {
      "NetNPA%": 0.011200000000000002
    },
    {
      "RawPDF": "/company/source/quarter/1480/6/2025/"
    }
  ],
  "2025-09-01": [
    {
      "Revenue ": 11609.0
    },
    {
      "Interest": 7199.0
    },
    {
      "Expenses ": 6644.0
    },
    {
      "FinancingProfit": -2235.0
    },
    {
      "FinancingMargin%": -0.19
    },
    {
      "OtherIncome ": 1651.0
    },
    {
      "Depreciation": 0.0
    },
    {
      "Profitbeforetax": -584.0
    },
    {
      "Tax%": -0.25
    },
    {
      "NetProfit ": -437.0
    },
    {
      "EPSinRs": -5.61
    },
    {
      "GrossNPA%": 0.036000000000000004
    },
    {
      "NetNPA%": 0.0104
    },
    {
      "RawPDF": "/company/source/quarter/1480/9/2025/"
    }
  ],
  "2025-12-01": [
    {
      "Revenue ": 11373.0
    },
    {
      "Interest": 6811.0
    },
    {
      "Expenses ": 6095.0
    },
    {
      "FinancingProfit": -1533.0
    },
    {
      "FinancingMargin%": -0.13
    },
    {
      "OtherIncome ": 1707.0
    },
    {
      "Depreciation": 0.0
    },
    {
      "Profitbeforetax": 174.0
    },
    {
      "Tax%": 0.26
    },
    {
      "NetProfit ": 128.0
    },
    {
      "EPSinRs": 1.64
    },
    {
      "GrossNPA%": 0.0356
    },
    {
      "NetNPA%": 0.0104
    },
    {
      "RawPDF": "/company/source/quarter/1480/12/2025/"
    }
  ]
}
